.gitignore
MANIFEST.in
README.rst
setup.cfg
setup.py
docs/HISTORY.txt
docs/LICENSE.GPL
docs/LICENSE.txt
docs/MANUAL.txt
raptus/__init__.py
raptus.article.upload.egg-info/PKG-INFO
raptus.article.upload.egg-info/SOURCES.txt
raptus.article.upload.egg-info/dependency_links.txt
raptus.article.upload.egg-info/entry_points.txt
raptus.article.upload.egg-info/namespace_packages.txt
raptus.article.upload.egg-info/not-zip-safe
raptus.article.upload.egg-info/requires.txt
raptus.article.upload.egg-info/top_level.txt
raptus/article/__init__.py
raptus/article/upload/__init__.py
raptus/article/upload/configure.zcml
raptus/article/upload/profiles/default/cssregistry.xml
raptus/article/upload/profiles/default/metadata.xml
raptus/article/upload/profiles/default/propertiestool.xml
raptus/article/upload/profiles/default/skins.xml
raptus/article/upload/skins/raptus_article_upload/raptus.article.upload.css.dtml