Metadata-Version: 1.0
Name: raptus.article.upload
Version: 2.0b6
Summary: Provides multiupload functionality for articles using collective.quickupload
Home-page: https://github.com/Raptus/raptus.article.upload
Author: Raptus AG
Author-email: dev@raptus.com
License: GPL
Platform: UNKNOWN
Classifier: Programming Language :: Python
Classifier: Topic :: Software Development :: Libraries :: Python Modules
